extraction_network/__init__.py
extraction_network/extraction_network.py
extraction_network/main.py
extraction_network/network_metrics.py
extraction_network-0.0.3.dist-info/DESCRIPTION.rst
extraction_network-0.0.3.dist-info/METADATA
extraction_network-0.0.3.dist-info/RECORD
extraction_network-0.0.3.dist-info/WHEEL
extraction_network-0.0.3.dist-info/metadata.json
extraction_network-0.0.3.dist-info/top_level.txt
